{
  "version": "7",
  "dialect": "postgresql",
  "id": "0007_enable_rls_security",
  "prevId": "0005_supreme_diamondback",
  "tables": {
    "public.users": {
      "name": "users",
      "schema": "public",
      "columns": {
        "id": {
          "name": "id",
          "type": "text",
          "primaryKey": true,
          "notNull": true,
          "default": "uuid_generate_v4()"
        },
        "email": {
          "name": "email",
          "type": "text",
          "notNull": true,
          "unique": true
        },
        "passwordHash": {
          "name": "passwordHash",
          "type": "text",
          "notNull": true
        },
        "instaAccessToken": {
          "name": "instaAccessToken",
          "type": "text"
        },
        "locale": {
          "name": "locale",
          "type": "text",
          "default": "en"
        },
        "stripeCustomerId": {
          "name": "stripe_customer_id",
          "type": "text"
        },
        "subscriptionStatus": {
          "name": "subscription_status",
          "type": "text",
          "default": "free"
        },
        "subscriptionPlan": {
          "name": "subscription_plan",
          "type": "text",
          "default": "free"
        },
        "subscriptionStartDate": {
          "name": "subscription_start_date",
          "type": "timestamp"
        },
        "subscriptionEndDate": {
          "name": "subscription_end_date",
          "type": "timestamp"
        },
        "isPro": {
          "name": "is_pro",
          "type": "boolean",
          "default": false
        },
        "createdAt": {
          "name": "createdAt",
          "type": "timestamp",
          "default": "now()",
          "notNull": true
        },
        "updatedAt": {
          "name": "updatedAt",
          "type": "timestamp",
          "default": "now()",
          "notNull": true
        }
      },
      "indexes": {},
      "foreignKeys": {},
      "primaryKeys": [
        "id"
      ],
      "uniqueConstraints": [
        "email"
      ]
    },
    "public.personas": {
      "name": "personas",
      "schema": "public",
      "columns": {
        "id": {
          "name": "id",
          "type": "uuid",
          "primaryKey": true,
          "default": "gen_random_uuid()"
        },
        "userId": {
          "name": "userId",
          "type": "uuid",
          "notNull": true,
          "references": {
            "table": "users",
            "column": "id"
          }
        },
        "data": {
          "name": "data",
          "type": "jsonb",
          "notNull": true
        },
        "createdAt": {
          "name": "createdAt",
          "type": "timestamp",
          "default": "now()",
          "notNull": true
        },
        "updatedAt": {
          "name": "updatedAt",
          "type": "timestamp",
          "default": "now()",
          "notNull": true
        }
      },
      "indexes": {},
      "foreignKeys": {
        "userId": {
          "table": "users",
          "column": "id"
        }
      },
      "primaryKeys": [
        "id"
      ]
    },
    "public.subscriptions": {
      "name": "subscriptions",
      "schema": "public",
      "columns": {
        "subscriptionId": {
          "name": "subscription_id",
          "type": "text",
          "primaryKey": true
        },
        "customerId": {
          "name": "customer_id",
          "type": "text",
          "notNull": true
        },
        "userId": {
          "name": "user_id",
          "type": "text",
          "notNull": true,
          "references": {
            "table": "users",
            "column": "id",
            "onDelete": "cascade"
          }
        },
        "status": {
          "name": "status",
          "type": "text",
          "notNull": true
        },
        "cancelAtPeriodEnd": {
          "name": "cancel_at_period_end",
          "type": "boolean",
          "notNull": true,
          "default": false
        },
        "currentPeriodStart": {
          "name": "current_period_start",
          "type": "timestamp with time zone"
        },
        "currentPeriodEnd": {
          "name": "current_period_end",
          "type": "timestamp with time zone"
        },
        "trialEnd": {
          "name": "trial_end",
          "type": "timestamp with time zone"
        },
        "priceId": {
          "name": "price_id",
          "type": "text"
        },
        "productId": {
          "name": "product_id",
          "type": "text"
        },
        "plan": {
          "name": "plan",
          "type": "text",
          "notNull": true
        },
        "quantity": {
          "name": "quantity",
          "type": "integer",
          "notNull": true,
          "default": 1
        },
        "latestInvoiceId": {
          "name": "latest_invoice_id",
          "type": "text"
        },
        "createdAt": {
          "name": "created_at",
          "type": "timestamp with time zone",
          "default": "now()"
        },
        "updatedAt": {
          "name": "updated_at",
          "type": "timestamp with time zone",
          "default": "now()"
        }
      },
      "indexes": {},
      "foreignKeys": {
        "userId": {
          "table": "users",
          "column": "id",
          "onDelete": "cascade"
        }
      },
      "primaryKeys": [
        "subscription_id"
      ]
    },
    "public.webhook_events": {
      "name": "webhook_events",
      "schema": "public",
      "columns": {
        "eventId": {
          "name": "event_id",
          "type": "text",
          "primaryKey": true
        },
        "type": {
          "name": "type",
          "type": "text",
          "notNull": true
        },
        "objectId": {
          "name": "object_id",
          "type": "text"
        },
        "status": {
          "name": "status",
          "type": "text",
          "notNull": true
        },
        "error": {
          "name": "error",
          "type": "text"
        },
        "processedAt": {
          "name": "processed_at",
          "type": "timestamp with time zone",
          "notNull": true
        }
      },
      "indexes": {},
      "foreignKeys": {},
      "primaryKeys": [
        "event_id"
      ]
    }
  }
}


